tests
livefyre
