Metadata-Version: 1.1
Name: python-livefyre
Version: 0.1.3
Summary: API wrapper for Livefyre v3
Home-page: https://github.com/jnovinger/python-livefyre
Author: Jason Novinger
Author-email: jnovinger@gmail.com
License: BSD
Keywords: python-livefyre
Platform: UNKNOWN
Classifier: Development Status :: 2 - Pre-Alpha
Classifier: Intended Audience :: Developers
Classifier: License :: OSI Approved :: BSD License
Classifier: Natural Language :: English
Classifier: Programming Language :: Python :: 2
Classifier: Programming Language :: Python :: 2.7
